py_mcws/Events.py
py_mcws/__init__.py
py_mcws/server.py
py_mcws-2.0.2.dist-info/LICENSE
py_mcws-2.0.2.dist-info/METADATA
py_mcws-2.0.2.dist-info/WHEEL
py_mcws-2.0.2.dist-info/top_level.txt
py_mcws-2.0.2.dist-info/RECORD
