Metadata-Version: 2.1
Name: py-mcws
Version: 2.0.2
Summary: Minecraft Bedrock WebSocket
Home-page: https://github.com/HRTK92/py-mcws
Author: HRTK92
License: MIT
License-File: LICENSE
Requires-Dist: websockets
